{
	"configurations" : 
	[
		{
			"directories" : 
			[
				{
					"build" : ".",
					"hasInstallRule" : true,
					"jsonFile" : "directory-.-7efaca17e736d5c494f9.json",
					"minimumCMakeVersion" : 
					{
						"string" : "3.12"
					},
					"projectIndex" : 0,
					"source" : ".",
					"targetIndexes" : 
					[
						0,
						1
					]
				}
			],
			"name" : "",
			"projects" : 
			[
				{
					"directoryIndexes" : 
					[
						0
					],
					"name" : "arm5dof_moveit_config",
					"targetIndexes" : 
					[
						0,
						1
					]
				}
			],
			"targets" : 
			[
				{
					"directoryIndex" : 0,
					"id" : "arm5dof_moveit_config_uninstall::@6890427a1f51a3e7e1df",
					"jsonFile" : "target-arm5dof_moveit_config_uninstall-aee903df38f2f75632c3.json",
					"name" : "arm5dof_moveit_config_uninstall",
					"projectIndex" : 0
				},
				{
					"directoryIndex" : 0,
					"id" : "uninstall::@6890427a1f51a3e7e1df",
					"jsonFile" : "target-uninstall-aff22078e7124871f4d6.json",
					"name" : "uninstall",
					"projectIndex" : 0
				}
			]
		}
	],
	"kind" : "codemodel",
	"paths" : 
	{
		"build" : "/home/zc/code/ws_arm5dof/src/build/arm5dof_moveit_config",
		"source" : "/home/zc/code/ws_arm5dof/src/arm5dof_moveit_config"
	},
	"version" : 
	{
		"major" : 2,
		"minor" : 3
	}
}
